ClearUtilities/ClearConfig.py
ClearUtilities/ClearEmail.py
ClearUtilities/ClearGPG.py
ClearUtilities/ClearHelpers.py
ClearUtilities/__init__.py
clearutilities-1.0.3.dist-info/METADATA
clearutilities-1.0.3.dist-info/WHEEL
clearutilities-1.0.3.dist-info/licenses/LICENSE
clearutilities-1.0.3.dist-info/RECORD
