Metadata-Version: 2.4
Name: ClearUtilities
Version: 1.0.3
Summary: Utility library for GnuPG and Email.
Project-URL: Homepage, https://github.com/bradleydonmorris/ClearUtilities
Project-URL: Issues, https://github.com/bradleydonmorris/ClearUtilities/issues
Author-email: Bradley Morris <bradleydonmorris@hotmail.com>
License-File: LICENSE
Classifier: License :: OSI Approved :: MIT License
Classifier: Operating System :: OS Independent
Classifier: Programming Language :: Python :: 3
Requires-Python: >=3.11
